whisperx_numpy2_compatibility/SubtitlesProcessor.py
whisperx_numpy2_compatibility/__init__.py
whisperx_numpy2_compatibility/__main__.py
whisperx_numpy2_compatibility/alignment.py
whisperx_numpy2_compatibility/asr.py
whisperx_numpy2_compatibility/assets/mel_filters.npz
whisperx_numpy2_compatibility/audio.py
whisperx_numpy2_compatibility/conjunctions.py
whisperx_numpy2_compatibility/diarize.py
whisperx_numpy2_compatibility/transcribe.py
whisperx_numpy2_compatibility/types.py
whisperx_numpy2_compatibility/utils.py
whisperx_numpy2_compatibility/vad.py
whisperx_numpy2_compatibility-0.1.1.dist-info/LICENSE
whisperx_numpy2_compatibility-0.1.1.dist-info/METADATA
whisperx_numpy2_compatibility-0.1.1.dist-info/WHEEL
whisperx_numpy2_compatibility-0.1.1.dist-info/entry_points.txt
whisperx_numpy2_compatibility-0.1.1.dist-info/RECORD
